{
  "page": "city-beijing",
  "route": "/city-kits/beijing",
  "screenshot": "city-beijing-390.png",
  "responseStatus": 200,
  "browserIssues": [],
  "title": "Beijing First Trip Kit | First China Trip Kit",
  "pathname": "/city-kits/beijing",
  "viewport": {
    "width": 390,
    "height": 844
  },
  "documentWidth": 390,
  "documentHeight": 19363,
  "horizontalScroll": false,
  "h1Count": 1,
  "imageCount": 14,
  "failedImages": [],
  "missingAltImages": [],
  "emptyButtons": [],
  "ctaCount": 18,
  "unclickableCtas": [],
  "visibleTechnicalStatuses": [],
  "visibleDevelopmentIndicators": 1,
  "articleCount": 10,
  "headingCount": 35,
  "mainWidth": 390,
  "overflowingElements": [],
  "firstTwoImageSources": [
    "/images/cities/beijing-forbidden-city-courtyard.webp",
    "/images/cities/details/beijing-hutong-street.webp"
  ],
  "repeatedFirstImage": null,
  "hero": {
    "source": "/images/cities/beijing-forbidden-city-courtyard.webp",
    "alt": "Visitors walking through a courtyard in Beijing's Forbidden City",
    "displayWidth": 390,
    "displayHeight": 560,
    "intrinsicWidth": 390,
    "intrinsicHeight": 258,
    "objectFit": "cover",
    "objectPosition": "50% 50%",
    "cropRetention": 0.461
  },
  "navigationObstruction": false,
  "fixedOverlays": []
}
